linksys/__init__.py
linksys/actions.py
linksys/router.py
linksys/types.py
linksys_smart_wifi_api-0.1.0.dist-info/METADATA
linksys_smart_wifi_api-0.1.0.dist-info/WHEEL
linksys_smart_wifi_api-0.1.0.dist-info/RECORD
